README.md
setup.py
mlogger/__init__.py
mlogger/config.py
mlogger/container.py
mlogger/defaults.py
mlogger/stdout.py
mlogger.egg-info/PKG-INFO
mlogger.egg-info/SOURCES.txt
mlogger.egg-info/dependency_links.txt
mlogger.egg-info/requires.txt
mlogger.egg-info/top_level.txt
mlogger/metric/__init__.py
mlogger/metric/base.py
mlogger/metric/history.py
mlogger/metric/to_float.py
mlogger/plotter/__init__.py
mlogger/plotter/graph.py
mlogger/plotter/text.py
mlogger/plotter/visdom_plotter.py
test/__init__.py
test/test_config.py
test/test_container.py
test/test_metrics.py