Metadata-Version: 1.0
Name: mlogger
Version: 1.0.1a0
Summary: A Machine Learning logger
Home-page: https://github.com/oval-group/mlogger
Author: Leonard Berrada
Author-email: UNKNOWN
License: MIT License
Platform: UNKNOWN
